README.rst
setup.py
python_walmart.egg-info/PKG-INFO
python_walmart.egg-info/SOURCES.txt
python_walmart.egg-info/dependency_links.txt
python_walmart.egg-info/requires.txt
python_walmart.egg-info/top_level.txt
tests/__init__.py
tests/conftest.py
tests/mocks.py
tests/test_walmart.py
walmart/__init__.py
walmart/exceptions.py
walmart/walmart.py