Metadata-Version: 1.1
Name: python-walmart
Version: 0.1.6
Summary: Walmart Marketplace API
Home-page: https://github.com/fulfilio/python-walmart
Author: Fulfil.IO Inc.
Author-email: hello@fulfil.io
License: UNKNOWN
Platform: UNKNOWN
Classifier: Development Status :: 2 - Pre-Alpha
Classifier: Programming Language :: Python
Classifier: Programming Language :: Python :: 2
Classifier: Programming Language :: Python :: 2.7
Classifier: Programming Language :: Python :: 3
Classifier: Programming Language :: Python :: 3.4
Classifier: Programming Language :: Python :: 3.5
